{
  "url": "https://www.ato.gov.au/individuals-and-families/paying-the-ato/help-with-paying",
  "title": "Help with paying",
  "description": "If you can't pay on time, there are support options you can access to meet your tax and super obligations.",
  "nat_number": "",
  "quick_code": "50299",
  "date_updated": "2025-07-14T14:00:00Z",
  "first_published": "",
  "keywords": "paying, payment help, payment plan, payment plans, managing payments, HELP deferral, SFSS deferral, financial difficulty, serious hardship, help with paying, pay tax, bill, debt, hardship, interest, interest-free payments, late payment, make a payment, payment arrangement, payments, tax debts, tax obligations, interest-free, secured payment plan, securities",
  "content_blocks": [
    {
      "type": "heading",
      "level": 2,
      "text": "What deferring means"
    },
    {
      "type": "paragraph",
      "text": "If you have a loan with the ATO (which includes a compulsory repayment or overseas levy) and you can't pay on time, you may apply to defer or amend your compulsory repayment or overseas levy."
    },
    {
      "type": "paragraph",
      "text": "This means we will either:"
    },
    {
      "type": "list",
      "ordered": false,
      "items": [
        "not raise a repayment (defer)",
        "reduce the amount of repayment required toward your loan (amend)."
      ]
    },
    {
      "type": "heading",
      "level": 2,
      "text": "When to apply to defer"
    },
    {
      "type": "paragraph",
      "text": "You may apply to defer or amend your compulsory repayment or overseas levy if:"
    },
    {
      "type": "list",
      "ordered": false,
      "items": [
        "making your repayment would cause you serious hardship",
        "there are other special reasons, for example natural disasters affecting you death or serious illness other serious or difficult circumstances."
      ]
    },
    {
      "type": "paragraph",
      "text": "If you apply to defer or amend your repayment under serious hardship, we will ask you for a detailed statement of your household income and expenditure to justify your claim."
    },
    {
      "type": "paragraph",
      "text": "We may also ask you to provide further details of income and expenditure and evidence, such as a copy of your most recent payslip."
    },
    {
      "type": "paragraph",
      "text": "If you have special circumstances and need to apply to defer or amend your repayment, complete a Defer or amend your compulsory repayment or overseas levy form (NAT 2471)."
    },
    {
      "type": "paragraph",
      "text": "For more information see Tax support for individuals ."
    },
    {
      "type": "heading",
      "level": 2,
      "text": "How to apply for deferral"
    },
    {
      "type": "paragraph",
      "text": "To apply for a deferral see Defer or amend your compulsory repayment or overseas levy ."
    },
    {
      "type": "paragraph",
      "text": "For more information see Contact us – Individuals enquiries"
    },
    {
      "type": "heading",
      "level": 2,
      "text": "Support for people experiencing vulnerability"
    },
    {
      "type": "paragraph",
      "text": "If you're facing challenging personal circumstances and need extra help managing your tax obligations, visit Tax support when you need it most for other support options available to people experiencing vulnerability."
    },
    {
      "type": "heading",
      "level": 2,
      "text": "How to use this document"
    },
    {
      "type": "paragraph",
      "text": "This information is written in a way that is easy to read."
    },
    {
      "type": "paragraph",
      "text": "We use pictures to explain some ideas."
    },
    {
      "type": "paragraph",
      "text": "We have also provided a PDF of this document so you can read this information offline – If you can't lodge or pay on time - Easy Read (PDF, 3.6MB) This link will download a file"
    },
    {
      "type": "table",
      "rows": [
        [
          "",
          "This document has been written by the Australian Tax Office or ATO."
        ],
        [
          "",
          "When you see the words 'we', 'our' or 'us' it means the ATO."
        ],
        [
          "",
          "This Easy Read document is a summary of another document."
        ],
        [
          "",
          "You can find the longer document on our website at www.ato.gov.au/Cant-Lodge-Or-Pay"
        ]
      ]
    },
    {
      "type": "heading",
      "level": 2,
      "text": "Lodging and paying tax"
    },
    {
      "type": "table",
      "rows": [
        [
          "",
          "When you earn money you may need to tell us about it ."
        ],
        [
          "",
          "This means you need to: lodge a tax return pay your tax bills by the due date pay your study or training loan."
        ],
        [
          "",
          "If you do not pay your tax bill by the due date it becomes a tax debt ."
        ],
        [
          "",
          "A tax debt is when you owe us money. For example, if you did not pay enough tax during the year you will owe us money."
        ],
        [
          "",
          "A tax return is a form you fill in each year and give to us. In the form you tell us how much money you made and how much tax you have already paid."
        ]
      ]
    },
    {
      "type": "heading",
      "level": 2,
      "text": "If you can not lodge or pay"
    },
    {
      "type": "table",
      "rows": [
        [
          "",
          "Talk to us as soon as possible if you can not: lodge a tax return pay your tax debt pay your study or training loan."
        ],
        [
          "",
          "To tell us about your situation, phone us on 13 11 42 during operating hours ."
        ],
        [
          "",
          "We will need to ask you some questions to prove who you are . This is to protect your information."
        ],
        [
          "This document tells you how to:"
        ],
        [
          "",
          "get help to lodge your tax"
        ],
        [
          "",
          "set up a payment plan to pay your tax"
        ],
        [
          "",
          "ask us to change your tax due date"
        ],
        [
          "",
          "ask us to change your tax amount."
        ]
      ]
    },
    {
      "type": "heading",
      "level": 2,
      "text": "Help to lodge"
    },
    {
      "type": "table",
      "rows": [
        [
          "",
          "You must lodge your tax return by 31 October."
        ],
        [
          "",
          "If you want to understand more about lodging tax we have 2 easier to read documents to help you: Get ready to do your tax How to do your tax"
        ],
        [
          "There are many ways to get help with lodging your tax return. You can use:"
        ],
        [
          "",
          "a tax agent"
        ],
        [
          "",
          "Tax Help"
        ],
        [
          "",
          "the National Tax Clinic program."
        ],
        [
          "",
          "If you can't use these services, you can phone us on 13 11 42 to talk to us about your situation."
        ],
        [
          "",
          "We will need to ask you some questions to prove who you are . This is to protect your information."
        ]
      ]
    },
    {
      "type": "heading",
      "level": 3,
      "text": "1. Tax agent"
    },
    {
      "type": "table",
      "rows": [
        [
          "",
          "A tax agent is a person who you pay to do your tax."
        ],
        [
          "",
          "Only registered tax agents can ask for money to do your tax."
        ],
        [
          "Registered means they:"
        ],
        [
          "",
          "have studied to become a tax agent"
        ],
        [
          "",
          "are on our list of tax agents."
        ],
        [
          "",
          "You can search for a registered tax agent at www.tpb.gov.au External Link"
        ]
      ]
    },
    {
      "type": "heading",
      "level": 3,
      "text": "2. Tax Help"
    },
    {
      "type": "table",
      "rows": [
        [
          "",
          "Tax Help is a group of people who help other people do their tax."
        ],
        [
          "",
          "They do not ask for any money to do this."
        ],
        [
          "",
          "We have trained these people to know about tax."
        ],
        [
          "",
          "Not everyone can use this service."
        ],
        [
          "",
          "Find out more about the Tax Help program ."
        ]
      ]
    },
    {
      "type": "heading",
      "level": 3,
      "text": "3. National Tax Clinic program"
    },
    {
      "type": "table",
      "rows": [
        [
          "",
          "The National Tax Clinic program can help people who: can not pay a tax agent do not meet the rules to use Tax Help are having money or personal problems."
        ],
        [
          "",
          "This program is: paid for by the government run by universities and TAFEs."
        ],
        [
          "",
          "Students who are learning about tax can help you for free."
        ],
        [
          "",
          "Trained managers make sure the students give you the right help."
        ],
        [
          "",
          "The students can help you: in person over the phone through a meeting online."
        ],
        [
          "",
          "You can also use this program if you are a small business."
        ],
        [
          "",
          "You need to meet the rules to use this program."
        ],
        [
          "",
          "Find out more about the National Tax Clinic program External Link ."
        ]
      ]
    },
    {
      "type": "heading",
      "level": 2,
      "text": "Help to pay"
    },
    {
      "type": "table",
      "rows": [
        [
          "We can help you if you can not:"
        ],
        [
          "",
          "pay all your tax"
        ],
        [
          "",
          "pay on time."
        ],
        [
          "",
          "If you have a tax debt you may be able to set up a payment plan . This is a way to pay using smaller payments over time."
        ],
        [
          "",
          "If you have a study or training loan you can ask us to defer or amend your payment . Defer means we can change the date of when you need to pay. Amend means we can change the amount you need to pay."
        ]
      ]
    },
    {
      "type": "heading",
      "level": 3,
      "text": "Payment plan"
    },
    {
      "type": "heading",
      "level": 4,
      "text": "Work out if a payment plan will help you"
    },
    {
      "type": "table",
      "rows": [
        [
          "To work out if a payment plan is a good idea for you, you need to know:"
        ],
        [
          "",
          "your tax debt"
        ],
        [
          "",
          "how much you need to pay straight away"
        ],
        [
          "",
          "how much you can afford to pay each week, fortnight or month. Fortnight means 2 weeks."
        ],
        [
          "",
          "You can use our payment plan estimator. The payment plan estimator is an online tool. It can help you work out your payment plan."
        ]
      ]
    },
    {
      "type": "heading",
      "level": 4,
      "text": "Use the payment plan estimator"
    },
    {
      "type": "table",
      "rows": [
        [
          "",
          "Open the payment plan estimator ."
        ],
        [
          "",
          "Put in how much your tax debt is. Only put numbers in. Do not put spaces or other symbols in."
        ],
        [
          "Pick when you will pay:"
        ],
        [
          "",
          "one payment a week one payment a fortnight one payment a month."
        ],
        [
          "",
          "a lump sum payment. Lump sum means you pay your whole tax debt at once."
        ],
        [
          "Choose a date. Select 'Show Result' to get your answer."
        ],
        [
          "",
          "If you select weekly, fortnightly or monthly payments you will need to pay an upfront amount. Upfront means the amount you must pay within 7 days."
        ],
        [
          "",
          "You can change the upfront amount to be more or less money."
        ],
        [
          "Then choose how to work out your payment plan. There are 2 ways you can do this."
        ],
        [
          "",
          "You can choose Repayment amounts. You will need to enter how much you will pay each time."
        ],
        [
          "",
          "Or you can choose Repayment periods. You will need to enter the start and end dates for your payments."
        ],
        [
          "Select 'Show Result' to get your answer."
        ],
        [
          "",
          "The tool will show you how much you must pay: in total upfront for each period in interest."
        ],
        [
          "",
          "You can print the results page to keep for your records."
        ]
      ]
    },
    {
      "type": "heading",
      "level": 4,
      "text": "Set up a payment plan"
    },
    {
      "type": "table",
      "rows": [
        [
          "After you use the payment plan estimator you can set up your payment plan with us."
        ],
        [
          "",
          "Read the important rules about payment plans first."
        ],
        [
          "To set up a payment plan you can:"
        ],
        [
          "",
          "Use ATO online services."
        ],
        [
          "",
          "Use our automated phone service on 13 28 65. Automated means you will not speak to a person. You will select numbers and symbols using your phone."
        ],
        [
          "",
          "Phone us on 13 11 42 and speak to a person. We will need to ask you some questions to prove who you are . This is to protect your information."
        ]
      ]
    },
    {
      "type": "heading",
      "level": 5,
      "text": "Use ATO online services"
    },
    {
      "type": "table",
      "rows": [
        [
          "",
          "You will need a myGov account linked to the ATO ."
        ],
        [
          "",
          "When you are logged into ATO online services, from the menu choose: Tax then choose Payment then choose Payment plans."
        ],
        [
          "You can:"
        ],
        [
          "",
          "set up your payment plan"
        ],
        [
          "",
          "choose to be sent SMS or email reminders about payments"
        ],
        [
          "",
          "view a summary of your payment plan"
        ],
        [
          "",
          "change or cancel your payment plan."
        ]
      ]
    },
    {
      "type": "heading",
      "level": 5,
      "text": "Use the automated phone service"
    },
    {
      "type": "table",
      "rows": [
        [
          "",
          "Call the phone service on 13 28 65 ."
        ],
        [
          "",
          "You can ask someone you trust to be with you to help you."
        ],
        [
          "Before you call you will need to know your:"
        ],
        [
          "",
          "tax file number ( TFN ) or Australian business number ( ABN )"
        ],
        [
          "",
          "total amount of your debt."
        ],
        [
          "",
          "Your TFN is a 9-digit number that identifies you in the tax and system."
        ],
        [
          "",
          "An ABN is an 11-digit number that a business uses to identify themselves when dealing with other business or with government."
        ],
        [
          "",
          "The phone service will tell you how to set up the payment plan. It is best to phone in business hours (8:00 am to 6:00 pm on weekdays Monday to Friday)."
        ],
        [
          "",
          "We will connect you to our call centre if you can not use the automated phone service."
        ]
      ]
    },
    {
      "type": "heading",
      "level": 3,
      "text": "Defer or amend your payment"
    },
    {
      "type": "table",
      "rows": [
        [
          "",
          "You may have a compulsory repayment for your study or training loan."
        ],
        [
          "",
          "Compulsory repayment means a payment you must make."
        ],
        [
          "",
          "You can ask us to defer or amend your compulsory repayment. Defer means you will not have to make a compulsory repayment for the next year."
        ],
        [
          "",
          "Amend means your payment for the year will be smaller."
        ],
        [
          "",
          "We can defer or amend if paying will be a serious hardship . Serious hardship is when it is hard to pay for basic living costs like food, housing, transport and medical treatment."
        ],
        [
          "You can also ask us to defer or amend your compulsory repayment if you have been affected by:"
        ],
        [
          "",
          "a natural disaster (like a flood, bushfire or cyclone)"
        ],
        [
          "",
          "serious illness (like cancer)"
        ],
        [
          "",
          "the death of a family member or close friend."
        ],
        [
          "",
          "You will need to provide us with evidence about your situation ."
        ]
      ]
    },
    {
      "type": "heading",
      "level": 4,
      "text": "Compulsory repayments you can ask us to defer or amend"
    },
    {
      "type": "table",
      "rows": [
        [
          "You can ask to defer or amend these types of compulsory repayments:"
        ],
        [
          "",
          "Higher Education Loan Program (HELP) Higher Education Contribution Scheme (HECS) VET Student Loan (VSL) Student Financial Supplement Scheme (SFSS) Student Start-up Loan (SSL) ABSTUDY Student Start-up Loan (ABSTUDY SSL) Australian Apprenticeship Support Loan (AASL) – previously known as Trade Support Loan (TSL) HELP, VSL or AASL overseas levy."
        ]
      ]
    },
    {
      "type": "heading",
      "level": 4,
      "text": "How to apply"
    },
    {
      "type": "table",
      "rows": [
        [
          "",
          "You need to fill out a form. You can find it at Defer or amend a repayment ."
        ],
        [
          "",
          "The form has information to help you answer the questions."
        ],
        [
          "",
          "You can ask someone you trust to help you fill out the form."
        ],
        [
          "",
          "If you can not fill out the form you can phone us on 1300 650 225 and we will help you."
        ],
        [
          "",
          "We will need to ask you some questions to prove who you are . This is to protect your information."
        ]
      ]
    },
    {
      "type": "heading",
      "level": 2,
      "text": "Need help?"
    },
    {
      "type": "table",
      "rows": [
        [
          "",
          "If you need help you can phone us on 13 11 42 ."
        ],
        [
          "",
          "We will need to ask you some questions to prove who you are . This is to protect your information."
        ],
        [
          "",
          "If you have difficulty hearing or speaking to people who use a phone, you can contact us through the National Relay Service (NRS)."
        ],
        [
          "",
          "You need to: Call the National Relay Service on 13 36 77 ask the Relay Officer to phone us on 13 11 42 ."
        ],
        [
          "",
          "If you want to speak in a language other than English, phone the Translating and Interpreting Service (TIS National) on 13 14 50 . Tell them: you want to speak to us the language you want to speak in."
        ]
      ]
    },
    {
      "type": "heading",
      "level": 2,
      "text": "Aboriginal and Torres Strait Islander languages"
    },
    {
      "type": "list",
      "ordered": false,
      "items": [
        "Alyawarr",
        "Anmatyerr",
        "Arrernte",
        "Burarra",
        "Kriol Eastside",
        "Kunwinjku",
        "Murrinh Patha",
        "Pintupi-Luritja (Luritja)",
        "Pitjantjatjara",
        "Tiwi",
        "Warlpiri",
        "Warumungu",
        "Yolngu Matha – Djambarrpuyngu",
        "Yumplatok"
      ]
    },
    {
      "type": "heading",
      "level": 2,
      "text": "Multicultural languages"
    },
    {
      "type": "list",
      "ordered": false,
      "items": [
        "Arabic / العربية",
        "Assyrian / ܐܵܬܘܿܪܵܝܵܐ",
        "Auslan",
        "বাংলা / Bengali",
        "မြန်မာ / Burmese",
        "Chaldean / كلداني",
        "简体中文主页/ Simplified Chinese",
        "繁體中文主頁 / Traditional Chinese",
        "Hrvatski / Croatian",
        "Dari / دری",
        "Thoŋ ee Jiëëŋ / Dinka",
        "Pilipino / Filipino",
        "Eλλŋνıĸa / Greek",
        "ગુજરાતી / Gujarati",
        "Hazaragi / هزاره گی",
        "हिन्दी / Hindi",
        "Bahasa Indonesia / Indonesian",
        "Italiano / Italian",
        "日本語 / Japanese",
        "ကညီကျိၥ် / Karen",
        "ភាសាខ្មែរ / Khmer",
        "한국어 / Korean",
        "नेपाली / Nepali",
        "Pashto / پشتو",
        "Persian (Farsi) / فارسی",
        "Português / Portuguese",
        "ਪੰਜਾਬੀ / Punjabi",
        "Русский / Russian",
        "සිංහල / Sinhalese",
        "Español / Spanish",
        "தமிழ் / Tamil",
        "ภาษาไทย / Thai",
        "Türkçe / Turkish",
        "Urdu / اردو",
        "Tiềng Việt / Vietnamese"
      ]
    },
    {
      "type": "heading",
      "level": 2,
      "text": "Educational support"
    },
    {
      "type": "paragraph",
      "text": "We offer free educational support to Aboriginal and Torres Strait Islander communities and culturally and linguistically diverse communities. We deliver informative, tailored presentations on tax and superannuation in Australia to help people understand their responsibilities, obligations and rights. We can also attend large community events that promote government services, if certain criteria are met."
    },
    {
      "type": "paragraph",
      "text": "If you want to know more about the support and education we provide, you can email us at CommunityEducation@ato.gov.au to request a presentation for community groups. All presentations are run virtually."
    },
    {
      "type": "heading",
      "level": 3,
      "text": "Watch and listen"
    },
    {
      "type": "list",
      "ordered": false,
      "items": [
        "atoTV – Aboriginal and Torres Strait Islander languages External Link",
        "atoTV – multicultural languages External Link",
        "Audio guides – multicultural languages",
        "Tax and super experiences – multicultural voices"
      ]
    },
    {
      "type": "heading",
      "level": 3,
      "text": "Read"
    },
    {
      "type": "list",
      "ordered": false,
      "items": [
        "Glossary of common tax and superannuation terms",
        "Tax time resources in languages other than English",
        "Forms, publications and factsheets for Aboriginal and Torres Strait Islander peoples External Link",
        "Forms, publications and factsheets for multicultural communities External Link (search for your language)"
      ]
    },
    {
      "type": "heading",
      "level": 2,
      "text": "Contact us"
    },
    {
      "type": "heading",
      "level": 3,
      "text": "Aboriginal and Torres Strait Islander peoples"
    },
    {
      "type": "paragraph",
      "text": "Aboriginal and Torres Strait Islander peoples can phone our Indigenous Helpline on 13 10 30 (8:00 am to 6:00 pm, Monday to Friday, except public holidays)."
    },
    {
      "type": "paragraph",
      "text": "Our Indigenous Helpline staff specialise in supporting Aboriginal and Torres Strait Islander peoples with things like getting a tax file number, lodging a tax return, or finding your super."
    },
    {
      "type": "heading",
      "level": 3,
      "text": "Translating and interpreting service"
    },
    {
      "type": "paragraph",
      "text": "If you would like to speak to us in a language other than English, you can use the Translating and Interpreting Service (TIS National)."
    },
    {
      "type": "paragraph",
      "text": "This free service provides an interpreter in one of these available languages External Link . The service will connect you and an interpreter to us so we can help with your query."
    },
    {
      "type": "paragraph",
      "text": "To contact TIS National, between 8:00 am and 6:00 pm AEST, Monday to Friday, phone:"
    },
    {
      "type": "list",
      "ordered": false,
      "items": [
        "13 14 50 if you're in Australia",
        "+61 3 9268 8332 if you're outside Australia."
      ]
    },
    {
      "type": "paragraph",
      "text": "TIS National does not provide interpreting services for Indigenous languages. Information about Indigenous interpreters External Link is available on the National Indigenous Australians Agency website."
    },
    {
      "type": "heading",
      "level": 3,
      "text": "Call services for hearing or speech/communication difficulties"
    },
    {
      "type": "paragraph",
      "text": "If you are d/Deaf, hard of hearing or have a speech/communication difficulty you can contact us through the National Relay Service External Link (NRS), as follows:"
    },
    {
      "type": "list",
      "ordered": true,
      "items": [
        "Contact the NRS through your preferred NRS call channel, detailed in NRS call numbers and links External Link .",
        "Provide the NRS with the ATO phone number you want to call."
      ]
    }
  ],
  "content_text": "## What deferring means\nIf you have a loan with the ATO (which includes a compulsory repayment or overseas levy) and you can't pay on time, you may apply to defer or amend your compulsory repayment or overseas levy.\nThis means we will either:\n- not raise a repayment (defer)\n- reduce the amount of repayment required toward your loan (amend).\n## When to apply to defer\nYou may apply to defer or amend your compulsory repayment or overseas levy if:\n- making your repayment would cause you serious hardship\n- there are other special reasons, for example natural disasters affecting you death or serious illness other serious or difficult circumstances.\nIf you apply to defer or amend your repayment under serious hardship, we will ask you for a detailed statement of your household income and expenditure to justify your claim.\nWe may also ask you to provide further details of income and expenditure and evidence, such as a copy of your most recent payslip.\nIf you have special circumstances and need to apply to defer or amend your repayment, complete a Defer or amend your compulsory repayment or overseas levy form (NAT 2471).\nFor more information see Tax support for individuals .\n## How to apply for deferral\nTo apply for a deferral see Defer or amend your compulsory repayment or overseas levy .\nFor more information see Contact us – Individuals enquiries\n## Support for people experiencing vulnerability\nIf you're facing challenging personal circumstances and need extra help managing your tax obligations, visit Tax support when you need it most for other support options available to people experiencing vulnerability.\n## How to use this document\nThis information is written in a way that is easy to read.\nWe use pictures to explain some ideas.\nWe have also provided a PDF of this document so you can read this information offline – If you can't lodge or pay on time - Easy Read (PDF, 3.6MB) This link will download a file\n | This document has been written by the Australian Tax Office or ATO.\n | When you see the words 'we', 'our' or 'us' it means the ATO.\n | This Easy Read document is a summary of another document.\n | You can find the longer document on our website at www.ato.gov.au/Cant-Lodge-Or-Pay\n## Lodging and paying tax\n | When you earn money you may need to tell us about it .\n | This means you need to: lodge a tax return pay your tax bills by the due date pay your study or training loan.\n | If you do not pay your tax bill by the due date it becomes a tax debt .\n | A tax debt is when you owe us money. For example, if you did not pay enough tax during the year you will owe us money.\n | A tax return is a form you fill in each year and give to us. In the form you tell us how much money you made and how much tax you have already paid.\n## If you can not lodge or pay\n | Talk to us as soon as possible if you can not: lodge a tax return pay your tax debt pay your study or training loan.\n | To tell us about your situation, phone us on 13 11 42 during operating hours .\n | We will need to ask you some questions to prove who you are . This is to protect your information.\nThis document tells you how to:\n | get help to lodge your tax\n | set up a payment plan to pay your tax\n | ask us to change your tax due date\n | ask us to change your tax amount.\n## Help to lodge\n | You must lodge your tax return by 31 October.\n | If you want to understand more about lodging tax we have 2 easier to read documents to help you: Get ready to do your tax How to do your tax\nThere are many ways to get help with lodging your tax return. You can use:\n | a tax agent\n | Tax Help\n | the National Tax Clinic program.\n | If you can't use these services, you can phone us on 13 11 42 to talk to us about your situation.\n | We will need to ask you some questions to prove who you are . This is to protect your information.\n### 1. Tax agent\n | A tax agent is a person who you pay to do your tax.\n | Only registered tax agents can ask for money to do your tax.\nRegistered means they:\n | have studied to become a tax agent\n | are on our list of tax agents.\n | You can search for a registered tax agent at www.tpb.gov.au External Link\n### 2. Tax Help\n | Tax Help is a group of people who help other people do their tax.\n | They do not ask for any money to do this.\n | We have trained these people to know about tax.\n | Not everyone can use this service.\n | Find out more about the Tax Help program .\n### 3. National Tax Clinic program\n | The National Tax Clinic program can help people who: can not pay a tax agent do not meet the rules to use Tax Help are having money or personal problems.\n | This program is: paid for by the government run by universities and TAFEs.\n | Students who are learning about tax can help you for free.\n | Trained managers make sure the students give you the right help.\n | The students can help you: in person over the phone through a meeting online.\n | You can also use this program if you are a small business.\n | You need to meet the rules to use this program.\n | Find out more about the National Tax Clinic program External Link .\n## Help to pay\nWe can help you if you can not:\n | pay all your tax\n | pay on time.\n | If you have a tax debt you may be able to set up a payment plan . This is a way to pay using smaller payments over time.\n | If you have a study or training loan you can ask us to defer or amend your payment . Defer means we can change the date of when you need to pay. Amend means we can change the amount you need to pay.\n### Payment plan\n#### Work out if a payment plan will help you\nTo work out if a payment plan is a good idea for you, you need to know:\n | your tax debt\n | how much you need to pay straight away\n | how much you can afford to pay each week, fortnight or month. Fortnight means 2 weeks.\n | You can use our payment plan estimator. The payment plan estimator is an online tool. It can help you work out your payment plan.\n#### Use the payment plan estimator\n | Open the payment plan estimator .\n | Put in how much your tax debt is. Only put numbers in. Do not put spaces or other symbols in.\nPick when you will pay:\n | one payment a week one payment a fortnight one payment a month.\n | a lump sum payment. Lump sum means you pay your whole tax debt at once.\nChoose a date. Select 'Show Result' to get your answer.\n | If you select weekly, fortnightly or monthly payments you will need to pay an upfront amount. Upfront means the amount you must pay within 7 days.\n | You can change the upfront amount to be more or less money.\nThen choose how to work out your payment plan. There are 2 ways you can do this.\n | You can choose Repayment amounts. You will need to enter how much you will pay each time.\n | Or you can choose Repayment periods. You will need to enter the start and end dates for your payments.\nSelect 'Show Result' to get your answer.\n | The tool will show you how much you must pay: in total upfront for each period in interest.\n | You can print the results page to keep for your records.\n#### Set up a payment plan\nAfter you use the payment plan estimator you can set up your payment plan with us.\n | Read the important rules about payment plans first.\nTo set up a payment plan you can:\n | Use ATO online services.\n | Use our automated phone service on 13 28 65. Automated means you will not speak to a person. You will select numbers and symbols using your phone.\n | Phone us on 13 11 42 and speak to a person. We will need to ask you some questions to prove who you are . This is to protect your information.\n##### Use ATO online services\n | You will need a myGov account linked to the ATO .\n | When you are logged into ATO online services, from the menu choose: Tax then choose Payment then choose Payment plans.\nYou can:\n | set up your payment plan\n | choose to be sent SMS or email reminders about payments\n | view a summary of your payment plan\n | change or cancel your payment plan.\n##### Use the automated phone service\n | Call the phone service on 13 28 65 .\n | You can ask someone you trust to be with you to help you.\nBefore you call you will need to know your:\n | tax file number ( TFN ) or Australian business number ( ABN )\n | total amount of your debt.\n | Your TFN is a 9-digit number that identifies you in the tax and system.\n | An ABN is an 11-digit number that a business uses to identify themselves when dealing with other business or with government.\n | The phone service will tell you how to set up the payment plan. It is best to phone in business hours (8:00 am to 6:00 pm on weekdays Monday to Friday).\n | We will connect you to our call centre if you can not use the automated phone service.\n### Defer or amend your payment\n | You may have a compulsory repayment for your study or training loan.\n | Compulsory repayment means a payment you must make.\n | You can ask us to defer or amend your compulsory repayment. Defer means you will not have to make a compulsory repayment for the next year.\n | Amend means your payment for the year will be smaller.\n | We can defer or amend if paying will be a serious hardship . Serious hardship is when it is hard to pay for basic living costs like food, housing, transport and medical treatment.\nYou can also ask us to defer or amend your compulsory repayment if you have been affected by:\n | a natural disaster (like a flood, bushfire or cyclone)\n | serious illness (like cancer)\n | the death of a family member or close friend.\n | You will need to provide us with evidence about your situation .\n#### Compulsory repayments you can ask us to defer or amend\nYou can ask to defer or amend these types of compulsory repayments:\n | Higher Education Loan Program (HELP) Higher Education Contribution Scheme (HECS) VET Student Loan (VSL) Student Financial Supplement Scheme (SFSS) Student Start-up Loan (SSL) ABSTUDY Student Start-up Loan (ABSTUDY SSL) Australian Apprenticeship Support Loan (AASL) – previously known as Trade Support Loan (TSL) HELP, VSL or AASL overseas levy.\n#### How to apply\n | You need to fill out a form. You can find it at Defer or amend a repayment .\n | The form has information to help you answer the questions.\n | You can ask someone you trust to help you fill out the form.\n | If you can not fill out the form you can phone us on 1300 650 225 and we will help you.\n | We will need to ask you some questions to prove who you are . This is to protect your information.\n## Need help?\n | If you need help you can phone us on 13 11 42 .\n | We will need to ask you some questions to prove who you are . This is to protect your information.\n | If you have difficulty hearing or speaking to people who use a phone, you can contact us through the National Relay Service (NRS).\n | You need to: Call the National Relay Service on 13 36 77 ask the Relay Officer to phone us on 13 11 42 .\n | If you want to speak in a language other than English, phone the Translating and Interpreting Service (TIS National) on 13 14 50 . Tell them: you want to speak to us the language you want to speak in.\n## Aboriginal and Torres Strait Islander languages\n- Alyawarr\n- Anmatyerr\n- Arrernte\n- Burarra\n- Kriol Eastside\n- Kunwinjku\n- Murrinh Patha\n- Pintupi-Luritja (Luritja)\n- Pitjantjatjara\n- Tiwi\n- Warlpiri\n- Warumungu\n- Yolngu Matha – Djambarrpuyngu\n- Yumplatok\n## Multicultural languages\n- Arabic / العربية\n- Assyrian / ܐܵܬܘܿܪܵܝܵܐ\n- Auslan\n- বাংলা / Bengali\n- မြန်မာ / Burmese\n- Chaldean / كلداني\n- 简体中文主页/ Simplified Chinese\n- 繁體中文主頁 / Traditional Chinese\n- Hrvatski / Croatian\n- Dari / دری\n- Thoŋ ee Jiëëŋ / Dinka\n- Pilipino / Filipino\n- Eλλŋνıĸa / Greek\n- ગુજરાતી / Gujarati\n- Hazaragi / هزاره گی\n- हिन्दी / Hindi\n- Bahasa Indonesia / Indonesian\n- Italiano / Italian\n- 日本語 / Japanese\n- ကညီကျိၥ် / Karen\n- ភាសាខ្មែរ / Khmer\n- 한국어 / Korean\n- नेपाली / Nepali\n- Pashto / پشتو\n- Persian (Farsi) / فارسی\n- Português / Portuguese\n- ਪੰਜਾਬੀ / Punjabi\n- Русский / Russian\n- සිංහල / Sinhalese\n- Español / Spanish\n- தமிழ் / Tamil\n- ภาษาไทย / Thai\n- Türkçe / Turkish\n- Urdu / اردو\n- Tiềng Việt / Vietnamese\n## Educational support\nWe offer free educational support to Aboriginal and Torres Strait Islander communities and culturally and linguistically diverse communities. We deliver informative, tailored presentations on tax and superannuation in Australia to help people understand their responsibilities, obligations and rights. We can also attend large community events that promote government services, if certain criteria are met.\nIf you want to know more about the support and education we provide, you can email us at CommunityEducation@ato.gov.au to request a presentation for community groups. All presentations are run virtually.\n### Watch and listen\n- atoTV – Aboriginal and Torres Strait Islander languages External Link\n- atoTV – multicultural languages External Link\n- Audio guides – multicultural languages\n- Tax and super experiences – multicultural voices\n### Read\n- Glossary of common tax and superannuation terms\n- Tax time resources in languages other than English\n- Forms, publications and factsheets for Aboriginal and Torres Strait Islander peoples External Link\n- Forms, publications and factsheets for multicultural communities External Link (search for your language)\n## Contact us\n### Aboriginal and Torres Strait Islander peoples\nAboriginal and Torres Strait Islander peoples can phone our Indigenous Helpline on 13 10 30 (8:00 am to 6:00 pm, Monday to Friday, except public holidays).\nOur Indigenous Helpline staff specialise in supporting Aboriginal and Torres Strait Islander peoples with things like getting a tax file number, lodging a tax return, or finding your super.\n### Translating and interpreting service\nIf you would like to speak to us in a language other than English, you can use the Translating and Interpreting Service (TIS National).\nThis free service provides an interpreter in one of these available languages External Link . The service will connect you and an interpreter to us so we can help with your query.\nTo contact TIS National, between 8:00 am and 6:00 pm AEST, Monday to Friday, phone:\n- 13 14 50 if you're in Australia\n- +61 3 9268 8332 if you're outside Australia.\nTIS National does not provide interpreting services for Indigenous languages. Information about Indigenous interpreters External Link is available on the National Indigenous Australians Agency website.\n### Call services for hearing or speech/communication difficulties\nIf you are d/Deaf, hard of hearing or have a speech/communication difficulty you can contact us through the National Relay Service External Link (NRS), as follows:\n- Contact the NRS through your preferred NRS call channel, detailed in NRS call numbers and links External Link .\n- Provide the NRS with the ATO phone number you want to call.",
  "child_links": [
    {
      "title": "Payment plans",
      "description": "How to set up a manageable payment plan to pay the tax you owe.",
      "url": "https://www.ato.gov.au/individuals-and-families/paying-the-ato/help-with-paying/payment-plans"
    },
    {
      "title": "Managing payments",
      "description": "How to prevent tax debt, make prepayments and payment transfers, and more.",
      "url": "https://www.ato.gov.au/individuals-and-families/paying-the-ato/help-with-paying/managing-payments"
    },
    {
      "title": "Compromise of tax debt",
      "description": "Find out what happens in a compromise of tax debt and how to apply for one.",
      "url": "https://www.ato.gov.au/individuals-and-families/paying-the-ato/help-with-paying/compromise-of-tax-debt"
    }
  ],
  "word_count": 2749,
  "source_title": "",
  "source_description": "",
  "category": "paying-the-ato"
}