{
  "url": "https://www.ato.gov.au/individuals-and-families/super-for-individuals-and-families/self-managed-super-funds-smsf/smsf-newsroom",
  "title": "SMSF newsroom",
  "description": "Read the latest updates on tax, super and registry services for self-managed super funds (SMSFs) and approved auditors.",
  "nat_number": "",
  "quick_code": "71096",
  "date_updated": "2023-03-16T14:00:00Z",
  "first_published": "",
  "keywords": "SMSF, newsroom, news, articles, self-manager super fund",
  "content_blocks": [
    {
      "type": "paragraph",
      "text": "If you haven't already, subscribe to our monthly newsletter and we'll send you regular news updates."
    },
    {
      "type": "paragraph",
      "text": "Using keywords, you can search for recent articles of interest."
    }
  ],
  "content_text": "If you haven't already, subscribe to our monthly newsletter and we'll send you regular news updates.\nUsing keywords, you can search for recent articles of interest.",
  "child_links": [],
  "word_count": 26,
  "source_title": "SMSF newsroom | Australian Taxation Office",
  "source_description": "Read the latest updates on tax, super and registry services for self-managed super funds (SMSFs) and approved auditors.",
  "category": "super-for-individuals-and-families"
}